iprpc/__init__.py
iprpc/aioapp.py
iprpc/aiohttp.py
iprpc/executor.py
iprpc/jsonrpc.py
iprpc-0.2.3.dist-info/WHEEL
iprpc-0.2.3.dist-info/METADATA
iprpc-0.2.3.dist-info/RECORD
