Metadata-Version: 2.1
Name: iprpc
Version: 0.2.3
Summary: InPlat JSON RPC library
Home-page: https://gitlab.app.ipl/inplat/iprpc/
License: Apache-2.0
Keywords: iprpc
Author: Konstantin Stepanov
Requires-Python: >=3.6,<4.0
Classifier: Development Status :: 2 - Pre-Alpha
Classifier: Intended Audience :: Developers
Classifier: License :: OSI Approved :: Apache Software License
Classifier: Natural Language :: English
Classifier: Programming Language :: Python :: 3
Classifier: Programming Language :: Python :: 3.6
Classifier: Programming Language :: Python :: 3.7
Classifier: Programming Language :: Python :: 3.8
Classifier: Programming Language :: Python :: 3.9
Provides-Extra: aioapp
Provides-Extra: aiohttp
Requires-Dist: aioapp-http (>=0.0.1b6,<0.0.2); extra == "aioapp"
Requires-Dist: aiohttp (>=3.4.4,<4.0.0); extra == "aiohttp"
Requires-Dist: jsonschema (>=3.2.0,<4.0.0)
Requires-Dist: pydantic (>=1.4,<2.0)
Requires-Dist: strict-rfc3339 (>=0.7,<0.8)
Requires-Dist: tinyrpc (>=1.0.4,<2.0.0)
